{
    "configurations": [
        {
            "name": "Linux",
            "includePath": [
                "/opt/ros/dashing/include",
                "${workspaceFolder}/include",
                "${workspaceFolder}/../../install/controller_parameter_server/include",
                "${workspaceFolder}/../../install/parameter_server_interfaces/include"
                
                
            ],
            "intelliSenseMode": "gcc-x64",
            "compilerPath": "/usr/bin/gcc",
            "cStandard": "c11",
            "cppStandard": "c++17"
        }
    ],
    "version": 4
}